fastnorm.cp313-win_amd64.pyd
fastnorm_cpp-0.1.3.dist-info/METADATA
fastnorm_cpp-0.1.3.dist-info/WHEEL
fastnorm_cpp-0.1.3.dist-info/RECORD
