Metadata-Version: 2.2
Name: fastnorm_cpp
Version: 0.1.3
Summary: Test: A super fast C++ implementation of RMSNorm
Author-Email: Mario Raach <marioraach01@gmail.com>
License: MIT
Classifier: Programming Language :: Python :: 3
Classifier: Programming Language :: C++
Classifier: License :: OSI Approved :: MIT License
Requires-Python: >=3.10
Requires-Dist: numpy>=2.2.6
